mcp_tdo/__init__.py
mcp_tdo/__main__.py
mcp_tdo/models.py
mcp_tdo/server.py
mcp_tdo/tdo_client.py
mcp_tdo-0.1.2.dist-info/licenses/LICENSE
mcp_tdo-0.1.2.dist-info/METADATA
mcp_tdo-0.1.2.dist-info/WHEEL
mcp_tdo-0.1.2.dist-info/entry_points.txt
mcp_tdo-0.1.2.dist-info/top_level.txt
mcp_tdo-0.1.2.dist-info/RECORD
