Metadata-Version: 2.4
Name: mcp-tdo
Version: 0.1.2
Summary: MCP server for tdo note taking tool
Author-email: 2KAbhishek <keshri.abhishek63@gmail.com>
License-Expression: GPL-3.0-or-later
Project-URL: Homepage, https://github.com/2KAbhishek/mcp-tdo
Project-URL: Bug Tracker, https://github.com/2KAbhishek/mcp-tdo/issues
Classifier: Programming Language :: Python :: 3
Classifier: Operating System :: OS Independent
Requires-Python: >=3.10
License-File: LICENSE
Requires-Dist: mcp-server>=0.1.1
Requires-Dist: pydantic>=2.0.0
Provides-Extra: dev
Requires-Dist: pytest>=7.0.0; extra == "dev"
Requires-Dist: ruff>=0.1.0; extra == "dev"
Dynamic: license-file
